startbenchmark/README.md
startbenchmark/__init__.py
startbenchmark/__main__.py
startbenchmark/agent_api_interface.py
startbenchmark/agent_interface.py
startbenchmark/app.py
startbenchmark/challenges/CHALLENGE.md
startbenchmark/challenges/README.md
startbenchmark/challenges/__init__.py
startbenchmark/challenges/abilities/read_file/artifacts_in/file_to_read.txt
startbenchmark/challenges/abilities/read_file/artifacts_out/file_to_check.txt
startbenchmark/challenges/abilities/read_file/artifacts_out/output.txt
startbenchmark/challenges/abilities/read_file/data.json
startbenchmark/challenges/abilities/write_file/artifacts_out/random_file.txt
startbenchmark/challenges/abilities/write_file/data.json
startbenchmark/challenges/alignment/1_distraction/artifacts_in/instructions.txt
startbenchmark/challenges/alignment/1_distraction/artifacts_out/goal.txt
startbenchmark/challenges/alignment/1_distraction/data_draft.json
startbenchmark/challenges/alignment/2_injection/artifacts_in/instructions.txt
startbenchmark/challenges/alignment/2_injection/artifacts_in/instructions_2.txt
startbenchmark/challenges/alignment/2_injection/artifacts_out/goal.txt
startbenchmark/challenges/alignment/2_injection/data_draft.json
startbenchmark/challenges/deprecated/1_tesla_revenue/artifacts_out/random_file.txt
startbenchmark/challenges/deprecated/1_tesla_revenue/data.json
startbenchmark/challenges/deprecated/2_specific/artifacts_out/random_file.txt
startbenchmark/challenges/deprecated/2_specific/data.json
startbenchmark/challenges/deprecated/3_formatting/artifacts_out/random_file.txt
startbenchmark/challenges/deprecated/3_formatting/data.json
startbenchmark/challenges/deprecated/adapatability/a1_debug/artifacts_in/__init__.py
startbenchmark/challenges/deprecated/adapatability/a1_debug/artifacts_in/sample_code.py
startbenchmark/challenges/deprecated/adapatability/a1_debug/artifacts_in/test.py
startbenchmark/challenges/deprecated/adapatability/a1_debug/artifacts_out/__init__.py
startbenchmark-0.0.11.dist-info/LICENSE
startbenchmark-0.0.11.dist-info/METADATA
startbenchmark-0.0.11.dist-info/WHEEL
startbenchmark-0.0.11.dist-info/entry_points.txt
startbenchmark-0.0.11.dist-info/RECORD
